nh3pred/__init__.py
nh3pred/api.py
nh3pred/model_def.py
nh3pred/utils.py
nh3pred/data/final_model.pth
nh3pred-0.1.3.dist-info/METADATA
nh3pred-0.1.3.dist-info/WHEEL
nh3pred-0.1.3.dist-info/top_level.txt
nh3pred-0.1.3.dist-info/RECORD
