Metadata-Version: 2.4
Name: nh3pred
Version: 0.1.3
Summary: Predict ammonia emissions with a recurrent neural network model
Author-email: Armand Favrot <armand.favrot@inrae.fr>
Classifier: License :: OSI Approved :: MIT License
Classifier: Development Status :: 3 - Alpha
Classifier: Programming Language :: Python
Requires-Python: >=3.12.3
Requires-Dist: pandas>=2.2.3
Requires-Dist: torch>=2.5.0
Provides-Extra: build
Requires-Dist: build; extra == "build"
Requires-Dist: twine; extra == "build"
Provides-Extra: dev
Requires-Dist: pytest; extra == "dev"
